plainspeak/README.md
plainspeak/__init__.py
plainspeak/ast.py
plainspeak/cli/README.md
plainspeak/cli/__init__.py
plainspeak/cli/commands.py
plainspeak/cli/compat.py
plainspeak/cli/config_cmd.py
plainspeak/cli/handlers/__init__.py
plainspeak/cli/handlers/execution_handlers.py
plainspeak/cli/handlers/system_handlers.py
plainspeak/cli/handlers/translate_handlers.py
plainspeak/cli/parser.py
plainspeak/cli/plugins_cmd.py
plainspeak/cli/repl.py
plainspeak/cli/shell.py
plainspeak/cli/shell_commands.py
plainspeak/cli/shell_parsers.py
plainspeak/cli/shell_utils.py
plainspeak/cli/translate_cmd.py
plainspeak/cli/utils.py
plainspeak/cli/utils.py.bak
plainspeak/cli.py
plainspeak/config.py
plainspeak/context.py
plainspeak/core/README.md
plainspeak/core/commander.py
plainspeak/core/executor.py
plainspeak/core/i18n.py
plainspeak/core/llm/__init__.py
plainspeak/core/llm/base.py
plainspeak/core/llm/local.py
plainspeak/core/llm/parsers.py
plainspeak/core/llm/remote.py
plainspeak/core/llm.py
plainspeak/core/parser.py
plainspeak/core/sandbox.py
plainspeak/core/session.py
plainspeak/learning.py
plainspeak/llm_interface.py
plainspeak/parser.py
plainspeak/plugins/README.md
plainspeak/plugins/__init__.py
plainspeak/plugins/base.py
plainspeak/plugins/calendar.py
plainspeak/plugins/calendar.yaml
plainspeak/plugins/dataspeak/README.md
plainspeak/plugins/dataspeak/__init__.py
plainspeak/plugins/dataspeak/connection.py
plainspeak/plugins/dataspeak/export.py
plainspeak/plugins/dataspeak/manifest.yaml
plainspeak/plugins/dataspeak/security.py
plainspeak/plugins/dataspeak/sql_generator.py
plainspeak/plugins/dataspeak/util.py
plainspeak/plugins/dataspeak/visualization.py
plainspeak/plugins/email.py
plainspeak/plugins/email.yaml
plainspeak/plugins/file.py
plainspeak/plugins/git.py
plainspeak/plugins/git.yaml
plainspeak/plugins/manager.py
plainspeak/plugins/network.py
plainspeak/plugins/platform.py
plainspeak/plugins/sandbox.py
plainspeak/plugins/schemas.py
plainspeak/plugins/system.py
plainspeak-1.0.0.dist-info/METADATA
plainspeak-1.0.0.dist-info/WHEEL
plainspeak-1.0.0.dist-info/entry_points.txt
plainspeak-1.0.0.dist-info/RECORD
