Metadata-Version: 2.3
Name: plainspeak
Version: 1.0.0
Summary: Turns everyday English into real terminal commands and API calls.
License: MIT
Keywords: nlp,cli,automation,llm
Author: cschanhniem
Author-email: contact@plainspeak.pro
Requires-Python: >=3.11
Classifier: Development Status :: 4 - Beta
Classifier: Environment :: Console
Classifier: Intended Audience :: Developers
Classifier: License :: OSI Approved :: MIT License
Classifier: Programming Language :: Python :: 3
Classifier: Programming Language :: Python :: 3.11
Classifier: Topic :: Software Development :: Libraries :: Python Modules
Provides-Extra: cuda
Requires-Dist: cmd2 (>=2.4.3)
Requires-Dist: ctransformers (>=0.2.27)
Requires-Dist: ctransformers ; extra == "cuda"
Requires-Dist: jinja2 (>=3.1.3)
Requires-Dist: pydantic (>=2.5.3)
Requires-Dist: toml (>=0.10.2)
Requires-Dist: typer[all] (>=0.9.0)
Project-URL: Documentation, https://cschanhniem.github.io/plainspeak/
Project-URL: Homepage, https://cschanhniem.github.io/plainspeak/
Project-URL: Repository, https://github.com/cschanhniem/plainspeak
